.gitignore
.prospector.yaml
.pylintrc
LICENSE
MANIFEST.in
README.rst
manage.py
requirements.in
requirements.txt
run.sh
setup.cfg
setup.py
versioneer.py
.eggs/README.txt
qeventlog/__init__.py
qeventlog/_version.py
qeventlog/logs.py
qeventlog/main.py
qeventlog/models.py
qeventlog/qetask.py
qeventlog/qeventlog_manage.py
qeventlog/settings.py
qeventlog/tasks.py
qeventlog/urls.py
qeventlog.egg-info/PKG-INFO
qeventlog.egg-info/SOURCES.txt
qeventlog.egg-info/dependency_links.txt
qeventlog.egg-info/entry_points.txt
qeventlog.egg-info/not-zip-safe
qeventlog.egg-info/pbr.json
qeventlog.egg-info/requires.txt
qeventlog.egg-info/top_level.txt
qeventlog/_cfgtool/install
qeventlog/_cfgtool/logging.conf.templ
qeventlog/_cfgtool/qeventlog
qeventlog/_cfgtool/qeventlog.conf.templ
qeventlog/_cfgtool/qeventlog.upstart.conf.templ
qeventlog/migrations/0001_initial.py
qeventlog/migrations/0002_qtaskstate_task.py
qeventlog/migrations/0003_auto_20160503_0352.py
qeventlog/migrations/0004_auto_20160505_0359.py
qeventlog/migrations/0005_auto_20160509_2113.py
qeventlog/migrations/0006_auto_20160517_2251.py
qeventlog/migrations/__init__.py