Metadata-Version: 1.1
Name: qeventlog
Version: 0.6.post6
Summary: Celery job event logger 
Home-page: https://github.com/clearclaw/qeventlog
Author: J C Lawrence
Author-email: claw@kanga.nu
License: GPL v3
Keywords: celery event logger
Platform: UNKNOWN
Classifier: Development Status :: 4 - Beta
Classifier: Intended Audience :: Developers
Classifier: License :: OSI Approved :: GNU General Public License v3 or later (GPLv3+)
Classifier: Topic :: Utilities
